gen_course/__init__.py
gen_course/gen_answer_to_article_ques.py
gen_course/gen_article_images_prompts.py
gen_course/gen_audio_card.py
gen_course/gen_base.py
gen_course/gen_base_v2.py
gen_course/gen_base_v3.py
gen_course/gen_course_article_content.py
gen_course/gen_course_articles.py
gen_course/gen_course_articles_doc.py
gen_course/gen_course_articles_titles.py
gen_course/gen_course_articles_url.py
gen_course/gen_course_image_prompt.py
gen_course/gen_course_metadata.py
gen_course/gen_video_card.py
gen_course/models.py
gen_course/prompt_helper.py
gen_course/utils.py
microlearn_gen_course-0.0.33.dist-info/METADATA
microlearn_gen_course-0.0.33.dist-info/WHEEL
microlearn_gen_course-0.0.33.dist-info/top_level.txt
microlearn_gen_course-0.0.33.dist-info/RECORD
