Metadata-Version: 2.1
Name: microlearn_gen_course
Version: 0.0.33
Summary: A python package for generating microlearn course content
Home-page: https://github.com/AIprojectflow/gen_course
Project-URL: Bug Tracker, https://github.com/AIprojectflow/gen_course/issues
Project-URL: Changelog, https://github.com/AIprojectflow/gen_course/releases
Classifier: Programming Language :: Python :: 3
Classifier: License :: OSI Approved :: BSD License
Classifier: Intended Audience :: Developers
Requires-Python: >=3.8
Requires-Dist: microlearn-llm-factory>=0.0.9
